MANIFEST.in
README.md
setup.py
solr_to_es/__init__.py
solr_to_es/__main__.py
solr_to_es.egg-info/PKG-INFO
solr_to_es.egg-info/SOURCES.txt
solr_to_es.egg-info/dependency_links.txt
solr_to_es.egg-info/entry_points.txt
solr_to_es.egg-info/requires.txt
solr_to_es.egg-info/top_level.txt