Metadata-Version: 1.1
Name: solr-to-es
Version: 0.2.1
Summary: Export Solr Nodes to Elasticsearch Indexes
Home-page: https://github.com/o19s/solr-to-es
Author: Joe Lawson
Author-email: jlawson@o19s.com
License: Apache License, Version 2.0
Keywords: solr elasticsearch o19s
Platform: UNKNOWN
Classifier: Development Status :: 3 - Alpha
Classifier: Environment :: Console
Classifier: Intended Audience :: Developers
Classifier: Intended Audience :: System Administrators
Classifier: License :: OSI Approved :: Apache Software License
Classifier: Natural Language :: English
Classifier: Programming Language :: Python :: 2
Classifier: Programming Language :: Python :: 2.6
Classifier: Programming Language :: Python :: 2.7
Classifier: Topic :: Utilities
